{"data":[{"type":"accounts","id":"CW9409GQ8","attributes":{"name":"Trend","environment":"lgpd","awsaccount-id":"535919695577","security-package":true,"created-date":1612285628209,"last-notified-date":1612287513937,"last-checked-date":1612287512514,"last-monitoring-event-date":1612289821000,"has-real-time-monitoring":true,"access":null,"tags":["lgpd"],"cloud-type":"aws","managed-group-id":"7-16-Zh-c","subscription-type":"advanced"},"relationships":{"organisation":{"data":{"type":"organisations","id":"102943668500"}}}},{"type":"accounts","id":"3vYT_GJUp","attributes":{"name":"Assinatura do Visual Studio Enterprise","environment":null,"security-package":true,"created-date":1612287458482,"last-notified-date":1612475692149,"last-checked-date":1612475691720,"has-real-time-monitoring":false,"access":null,"tags":null,"cloud-type":"azure","cloud-data":{"azure":{"subscriptionId":"370fdd67-9cb7-46e1-8bf8-bbfd46ea750d"}},"managed-group-id":"4McOsXFEo","subscription-type":"essentials"},"relationships":{"organisation":{"data":{"type":"organisations","id":"102943668500"}}}}]}